autorminal/main.py
autorminal-0.1.1.dist-info/licenses/LICENSE
autorminal-0.1.1.dist-info/METADATA
autorminal-0.1.1.dist-info/WHEEL
autorminal-0.1.1.dist-info/entry_points.txt
autorminal-0.1.1.dist-info/top_level.txt
autorminal-0.1.1.dist-info/RECORD
