Metadata-Version: 2.4
Name: autorminal
Version: 0.1.1
Summary: A simple AI agent for unix-like terminal
Author-email: littzhch <2371050115@qq.com>
License: GLWTPL
Project-URL: Repository, https://github.com/littzhch/autorminal.git
Requires-Python: >=3.10
License-File: LICENSE
Requires-Dist: openai>=1.68.2
Requires-Dist: pyte>=0.8.2
Requires-Dist: psutil>=7.0.0
Dynamic: license-file
